mp4tolottie/__init__.py
mp4tolottie/cli.py
mp4tolottie/core/extractor.py
mp4tolottie/core/lottie_builder.py
mp4tolottie/core/pipeline.py
mp4tolottie/core/vectorizer.py
mp4tolottie-0.1.1.dist-info/METADATA
mp4tolottie-0.1.1.dist-info/WHEEL
mp4tolottie-0.1.1.dist-info/entry_points.txt
mp4tolottie-0.1.1.dist-info/top_level.txt
mp4tolottie-0.1.1.dist-info/RECORD
