Metadata-Version: 2.4
Name: mp4tolottie
Version: 0.1.1
Summary: Convert MP4 videos to vector-based Lottie JSON animations
Author-email: Muhammad Thabsheer N P <thabsheeron@gmail.com>
Requires-Python: >=3.7
Requires-Dist: pillow
